{"_id":7,"nama":"Al-Kautsar","arti":"Nikmat yang Melimpah","status_bookmark":false,"status_selesai":false,"daftar_ayat":[{"_id_surat":7,"_id":1,"nama_gambar":"gayat7_1","nama_ayat":"ayat7_1","terjemahan":"Sesungguhnya Kami telah memberikan kepadamu nikmat yang banyak.","status_bookmark":false,"status_selesai":false},{"_id_surat":7,"_id":2,"nama_gambar":"gayat7_2","nama_ayat":"ayat7_2","terjemahan":"Maka dirikanlah shalat karena Tuhanmu; dan berkorbanlah.","status_bookmark":false,"status_selesai":false},{"_id_surat":7,"_id":3,"nama_gambar":"gayat7_3","nama_ayat":"ayat7_3","terjemahan":"Sesungguhnya orang-orang yang membenci kamu dialah yang terputus.","status_bookmark":false,"status_selesai":false}]}